eventhooks/__init__.py
eventhooks/_version.py
eventhooks/event_helper.py
eventhooks/eventhooks.py
eventhooks/mail/__init__.py
eventhooks/mail/aws_ses.py
eventhooks/mail/environment_variables.py
eventhooks/mail/exceptions.py
eventhooks/mail/message.py
eventhooks/mail/simple.py
eventhooks-0.3.2.dist-info/METADATA
eventhooks-0.3.2.dist-info/WHEEL
eventhooks-0.3.2.dist-info/top_level.txt
eventhooks-0.3.2.dist-info/RECORD
