Metadata-Version: 2.1
Name: eventhooks
Version: 0.3.2
Summary: Trigger webhooks with events.
Home-page: https://github.com/normoes/events
Author: Norman Moeschter-Schenck
Author-email: norman.moeschter@gmail.com
Maintainer: Norman Moeschter-Schenck
Maintainer-email: <norman.moeschter@gmail.com>
License: UNKNOWN
Download-URL: https://github.com/normoes/events/archive/v0.3.2.tar.gz
Platform: UNKNOWN
Classifier: Development Status :: 5 - Production/Stable
Classifier: Intended Audience :: Developers
Classifier: License :: OSI Approved :: MIT License
Classifier: Natural Language :: English
Classifier: Programming Language :: Python
Requires-Dist: requests (>=2.24.0)
Provides-Extra: aws
Requires-Dist: boto3 (>=1.11.14) ; extra == 'aws'
Provides-Extra: rabbit
Requires-Dist: pika (>=1.2.0) ; extra == 'rabbit'
